CHANGELOG
LICENSE
MANIFEST.in
README.rst
setup.py
cacheops/__init__.py
cacheops/conf.py
cacheops/cross.py
cacheops/funcy.py
cacheops/invalidation.py
cacheops/jinja2.py
cacheops/models.py
cacheops/query.py
cacheops/simple.py
cacheops/urls.py
cacheops/utils.py
cacheops/views.py
cacheops/lua/cache_thing.lua
cacheops/lua/invalidate.lua
cacheops/management/__init__.py
cacheops/management/commands/__init__.py
cacheops/management/commands/cleanfilecache.py
cacheops/management/commands/invalidate.py
cacheops/templatetags/__init__.py
cacheops/templatetags/cacheops.py
django_cacheops_with_stats.egg-info/PKG-INFO
django_cacheops_with_stats.egg-info/SOURCES.txt
django_cacheops_with_stats.egg-info/dependency_links.txt
django_cacheops_with_stats.egg-info/not-zip-safe
django_cacheops_with_stats.egg-info/requires.txt
django_cacheops_with_stats.egg-info/top_level.txt